devart/salesforce/__init__.py
devart/salesforce/salesforce.cpython-39-x86_64-linux-gnu.so
devart/salesforce/salesforce.pyi
devart/salesforce/Salesforce/Devart.Python.SalesforceEngine.dll
devart/salesforce/Salesforce/Devart.Python.SalesforceEngine.runtimeconfig.json
devart/salesforce/Salesforce/Newtonsoft.Json.dll
devart/salesforce/Salesforce/System.Diagnostics.PerformanceCounter.dll
devart/salesforce/Salesforce/System.Private.ServiceModel.dll
devart/salesforce/Salesforce/System.ServiceModel.Http.dll
devart/salesforce/Salesforce/System.ServiceModel.Primitives.dll
devart/salesforce/Salesforce/libhostfxr.so
devart/salesforce/Salesforce/libsqlite3.so
devart/salesforce/Salesforce/shared/Microsoft.NETCore.App/6.0.19/.version
devart/salesforce/Salesforce/shared/Microsoft.NETCore.App/6.0.19/Microsoft.CSharp.dll
devart/salesforce/Salesforce/shared/Microsoft.NETCore.App/6.0.19/Microsoft.NETCore.App.deps.json
devart/salesforce/Salesforce/shared/Microsoft.NETCore.App/6.0.19/Microsoft.NETCore.App.runtimeconfig.json
devart/salesforce/Salesforce/shared/Microsoft.NETCore.App/6.0.19/Microsoft.VisualBasic.Core.dll
devart/salesforce/Salesforce/shared/Microsoft.NETCore.App/6.0.19/Microsoft.VisualBasic.dll
devart/salesforce/Salesforce/shared/Microsoft.NETCore.App/6.0.19/Microsoft.Win32.Primitives.dll
devart/salesforce/Salesforce/shared/Microsoft.NETCore.App/6.0.19/Microsoft.Win32.Registry.dll
devart/salesforce/Salesforce/shared/Microsoft.NETCore.App/6.0.19/System.AppContext.dll
devart/salesforce/Salesforce/shared/Microsoft.NETCore.App/6.0.19/System.Buffers.dll
devart/salesforce/Salesforce/shared/Microsoft.NETCore.App/6.0.19/System.Collections.Concurrent.dll
devart/salesforce/Salesforce/shared/Microsoft.NETCore.App/6.0.19/System.Collections.Immutable.dll
devart/salesforce/Salesforce/shared/Microsoft.NETCore.App/6.0.19/System.Collections.NonGeneric.dll
devart/salesforce/Salesforce/shared/Microsoft.NETCore.App/6.0.19/System.Collections.Specialized.dll
devart_salesforce_connector-1.2.0.dist-info/LICENSE.txt
devart_salesforce_connector-1.2.0.dist-info/METADATA
devart_salesforce_connector-1.2.0.dist-info/WHEEL
devart_salesforce_connector-1.2.0.dist-info/top_level.txt
devart_salesforce_connector-1.2.0.dist-info/RECORD
